python_lever/__init__.py
python_lever/jwt/__init__.py
python_lever/jwt/auth.py
python_lever/jwt/utils.py
python_lever-0.2.4.dist-info/LICENCE.txt
python_lever-0.2.4.dist-info/METADATA
python_lever-0.2.4.dist-info/WHEEL
python_lever-0.2.4.dist-info/top_level.txt
python_lever-0.2.4.dist-info/RECORD
