Metadata-Version: 2.1
Name: python-lever
Version: 0.2.4
Summary: Lever python custom packages
Home-page: https://github.com/fashtop3/lever-jwt.git
Author: Fashola Ayodeji
Author-email: fashtop3@gmail.com
License: MIT
Keywords: lever-auth
Platform: UNKNOWN
Classifier: Programming Language :: Python :: 3
Classifier: License :: OSI Approved :: MIT License
Classifier: Operating System :: OS Independent
Requires-Dist: pyjwt (==1.5.3)
Requires-Dist: flask
